__init__.py
config.py
pubsub.py
pubsubdil-0.0.7.dist-info/METADATA
pubsubdil-0.0.7.dist-info/WHEEL
pubsubdil-0.0.7.dist-info/top_level.txt
pubsubdil-0.0.7.dist-info/RECORD
